README.md
setup.py
hikyaku/__init__.py
hikyaku/base.py
hikyaku.egg-info/PKG-INFO
hikyaku.egg-info/SOURCES.txt
hikyaku.egg-info/dependency_links.txt
hikyaku.egg-info/not-zip-safe
hikyaku.egg-info/requires.txt
hikyaku.egg-info/top_level.txt
hikyaku/channels/__init__.py
hikyaku/channels/email.py
hikyaku/channels/slack.py