Metadata-Version: 1.2
Name: hikyaku
Version: 0.2.2
Summary: A messaging library that wraps multiple messaging protocols into one easy to use package.
Home-page: UNKNOWN
Author: Karim Shehadeh
Author-email: karim@karim.cloud
License: MIT
Keywords: messaging email slack notification communication
Platform: UNKNOWN
Classifier: Development Status :: 3 - Alpha
Classifier: Intended Audience :: Developers
Classifier: Topic :: Software Development :: Build Tools
Classifier: License :: OSI Approved :: MIT License
Classifier: Programming Language :: Python :: 3
Classifier: Programming Language :: Python :: 3.6
Requires-Python: >=3.6
